civitai/api/__init__.py
civitai/api/base.py
civitai/api/client.py
civitai/api/creators.py
civitai/api/images.py
civitai/api/model.py
civitai/api/model_version.py
civitai/api/models.py
civitai/api/tags.py
civitai/api_class/__init__.py
civitai/api_class/common.py
civitai/api_class/creator.py
civitai/api_class/image.py
civitai/api_class/metadata.py
civitai/api_class/model.py
civitai/api_class/model_list.py
civitai/api_class/model_version.py
civitai/api_class/tag.py
civitai_downloader/__init__.py
civitai_downloader/__main__.py
civitai_downloader/__version__.py
civitai_downloader/cli.py
civitai_downloader/client.py
civitai_downloader/downloader.py
civitai_downloader/login.py
civitai_downloader/main.py
civitai_downloader/api/download.py
civitai_downloader/api/user_agent.py
civitai_downloader/download/__init__.py
civitai_downloader/download/backend.py
civitai_downloader/download/download.py
civitai_downloader/download/file_name_extractor.py
civitai_downloader/download/handler.py
civitai_downloader/download/manager.py
civitai_downloader/download/util.py
civitai_downloader/env/__init__.py
civitai_downloader/env/jupyter.py
civitai_downloader/token/__init__.py
civitai_downloader/token/token.py
civitai_model_downloader-0.4.7.dist-info/licenses/LICENSE
civitai_model_downloader-0.4.7.dist-info/METADATA
civitai_model_downloader-0.4.7.dist-info/WHEEL
civitai_model_downloader-0.4.7.dist-info/entry_points.txt
civitai_model_downloader-0.4.7.dist-info/top_level.txt
civitai_model_downloader-0.4.7.dist-info/RECORD
