Metadata-Version: 2.4
Name: civitai-model-downloader
Version: 0.4.7
Summary: A package to download models from CivitAI
Author-email: Hyunbeen Chang <bean980310@gmail.com>
Maintainer-email: Hyunbeen Chang <bean980310@gmail.com>
License:                     GNU GENERAL PUBLIC LICENSE
Project-URL: Repository, https://github.com/bean980310/civitai-downloader
Project-URL: Bug Tracker, https://github.com/bean980310/civitai-downloader/issues
Project-URL: Changelog, https://github.com/bean980310/civitai-downloader/blob/master/CHANGELOG.md
Keywords: civitai
Classifier: Programming Language :: Python :: 3
Classifier: License :: OSI Approved :: GNU General Public License v3 or later (GPLv3+)
Classifier: Operating System :: OS Independent
Requires-Python: <3.13,>=3.9
License-File: LICENSE
Requires-Dist: requests
Requires-Dist: tqdm
Requires-Dist: ipywidgets
Requires-Dist: appdirs
Requires-Dist: urllib3
Requires-Dist: civitai-py
Requires-Dist: typer
Dynamic: license-file
